xrst/__init__.py
xrst/__main__.py
xrst/add_before_title.py
xrst/add_line_numbers.py
xrst/auto_file.py
xrst/auto_indent.py
xrst/check_input_files.py
xrst/check_page_name.py
xrst/code_command.py
xrst/comment_ch_command.py
xrst/comment_command.py
xrst/dir_command.py
xrst/file_line.py
xrst/get_conf_dict.py
xrst/get_file_info.py
xrst/get_spell_checker.py
xrst/indent_command.py
xrst/literal_command.py
xrst/newline_indices.py
xrst/next_heading.py
xrst/pattern.py
xrst/process_children.py
xrst/process_headings.py
xrst/ref_command.py
xrst/remove_line_numbers.py
xrst/rename_group.py
xrst/replace_spell.py
xrst/run_xrst.py
xrst/spell_command.py
xrst/sphinx_label.py
xrst/start_end_file.py
xrst/suspend_command.py
xrst/system_exit.py
xrst/table_of_contents.py
xrst/template_command.py
xrst/temporary_file.py
xrst/toc_commands.py
xrst-2026.0.0.dist-info/METADATA
xrst-2026.0.0.dist-info/WHEEL
xrst-2026.0.0.dist-info/entry_points.txt
xrst-2026.0.0.dist-info/top_level.txt
xrst-2026.0.0.dist-info/RECORD
