Metadata-Version: 2.4
Name: xrst
Version: 2026.0.0
Summary: Extract RST files from source code and run Sphinx
License: GPL-3.0-or-later
Project-URL: Documenttion, https://xrst.readthedocs.io/latest
Project-URL: ReleaseNotes, https://xrst.readthedocs.io/latest/release_notes.html
Project-URL: Repository, https://github.com/bradbell/xrst
Project-URL: Issues, https://github.com/bradbell/xrst/issues
Keywords: sphinx,rst,documentation,source
Classifier: Topic :: Documentation :: Sphinx
Classifier: Development Status :: 4 - Beta
Classifier: License :: OSI Approved
Classifier: Operating System :: OS Independent
Classifier: Environment :: Console
Classifier: Intended Audience :: Developers
Classifier: Natural Language :: English
Requires-Python: >=3.9
Requires-Dist: sphinx
Requires-Dist: tomli
Requires-Dist: sphinx-copybutton
Requires-Dist: pyspellchecker
Requires-Dist: furo
